easyvvuq/__init__.py
easyvvuq/_version.py
easyvvuq/base_element.py
easyvvuq/campaign.py
easyvvuq/constants.py
easyvvuq/data_structs.py
easyvvuq/params_specification.py
easyvvuq/actions/__init__.py
easyvvuq/actions/action_statuses.py
easyvvuq/actions/execute_kubernetes.py
easyvvuq/actions/execute_local.py
easyvvuq/actions/execute_qcgpj.py
easyvvuq/actions/execute_qcgpj_task.py
easyvvuq/actions/execute_slurm.py
easyvvuq/analysis/__init__.py
easyvvuq/analysis/base.py
easyvvuq/analysis/basic_stats.py
easyvvuq/analysis/ensemble_boot.py
easyvvuq/analysis/fd_analysis.py
easyvvuq/analysis/gp_analyse.py
easyvvuq/analysis/mcmc.py
easyvvuq/analysis/pce_analysis.py
easyvvuq/analysis/qmc_analysis.py
easyvvuq/analysis/results.py
easyvvuq/analysis/sc_analysis.py
easyvvuq/analysis/ssc_analysis.py
easyvvuq/comparison/__init__.py
easyvvuq/comparison/base.py
easyvvuq/comparison/validate.py
easyvvuq/db/__init__.py
easyvvuq/db/base.py
easyvvuq/db/sql.py
easyvvuq/decoders/__init__.py
easyvvuq/decoders/hdf5.py
easyvvuq/decoders/json.py
easyvvuq/decoders/robust_csv.py
easyvvuq/decoders/simple_csv.py
easyvvuq/decoders/yaml.py
easyvvuq/encoders/__init__.py
easyvvuq/encoders/copy_encoder.py
easyvvuq/encoders/directory_builder.py
easyvvuq/encoders/generic_template.py
easyvvuq/encoders/jinja_encoder.py
easyvvuq/encoders/multiencoder.py
easyvvuq/sampling/__init__.py
easyvvuq/sampling/base.py
easyvvuq/sampling/csv_sampler.py
easyvvuq/sampling/dataframe_sampler.py
easyvvuq/sampling/empty.py
easyvvuq/sampling/fd.py
easyvvuq/sampling/grid_sampler.py
easyvvuq/sampling/mc_sampler.py
easyvvuq/sampling/mcmc.py
easyvvuq/sampling/pce.py
easyvvuq/sampling/qmc.py
easyvvuq/sampling/quasirandom.py
easyvvuq/sampling/random.py
easyvvuq/sampling/replica_sampler.py
easyvvuq/sampling/sampler_of_samplers.py
easyvvuq/sampling/simplex_stochastic_collocation.py
easyvvuq/sampling/stochastic_collocation.py
easyvvuq/sampling/sweep.py
easyvvuq/sampling/transformations.py
easyvvuq/tools/external_encoder.py
easyvvuq-1.3.dist-info/licenses/COPYING
easyvvuq-1.3.dist-info/licenses/COPYING.LESSER
easyvvuq-1.3.dist-info/METADATA
easyvvuq-1.3.dist-info/WHEEL
easyvvuq-1.3.dist-info/top_level.txt
easyvvuq-1.3.dist-info/RECORD
