Metadata-Version: 2.4
Name: easyvvuq
Version: 1.3
Summary: Library to facilitate simple Verification, Validation and Uncertainty Quantification of simulation codes
Author: CCS
License: LGPL-3.0 AND GPL-3.0
Project-URL: Source, https://github.com/UCL-CCS/EasyVVUQ
Project-URL: Tracker, https://github.com/UCL-CCS/EasyVVUQ/issues
Project-URL: Documentation, https://easyvvuq.readthedocs.io/en/dev/
Requires-Python: >=3.8
License-File: COPYING
License-File: COPYING.LESSER
Requires-Dist: numpy<2
Requires-Dist: pandas
Requires-Dist: scipy
Requires-Dist: wheel
Requires-Dist: chaospy==4.3.2
Requires-Dist: numpoly==1.1.3
Requires-Dist: SALib
Requires-Dist: SQLAlchemy
Requires-Dist: cerberus
Requires-Dist: dask[complete]
Requires-Dist: dask_jobqueue
Requires-Dist: cloudpickle
Requires-Dist: scikit-learn
Requires-Dist: jinja2
Requires-Dist: kubernetes
Requires-Dist: squarify
Requires-Dist: dill
Requires-Dist: tqdm
Requires-Dist: qcg-pilotjob~=0.13.0
Requires-Dist: qcg-pilotjob-executor-api~=0.13.0
Requires-Dist: h5py
Requires-Dist: tomli
Requires-Dist: fipy
Requires-Dist: setuptools_scm
Provides-Extra: docs
Requires-Dist: sphinx>=5.3; extra == "docs"
Provides-Extra: tests
Requires-Dist: pytest>=3.3.0; extra == "tests"
Requires-Dist: pytest-pep8; extra == "tests"
Requires-Dist: pytest-benchmark; extra == "tests"
Requires-Dist: pytest-dependency; extra == "tests"
Provides-Extra: lint
Requires-Dist: black; extra == "lint"
Requires-Dist: ruff; extra == "lint"
Dynamic: license-file
